README
setup.py
titere/__init__.py
titere/main.py
titere/tags.py
titere/titere.py
titere/types.py
titere.egg-info/PKG-INFO
titere.egg-info/SOURCES.txt
titere.egg-info/dependency_links.txt
titere.egg-info/entry_points.txt
titere.egg-info/top_level.txt