Metadata-Version: 1.0
Name: titere
Version: 0.1
Summary: Automated toold that manage configurations
Home-page: http://pypi.python.org/pypi/titere/
Author: Jorge Eduardo Cardona
Author-email: jorgeecardona@gmail.com
License: BSD
Platform: UNKNOWN
Classifier: Development Status :: 3 - Alpha
Classifier: License :: OSI Approved :: BSD License
